Workbook

Sheet Summary
B2: Debt Given By Skalar | C2: ='Debt Given By Skalar Cohort Led'!C25 -> Date | D2: ='Debt Given By Skalar Cohort Led'!D25 -> 46181 | E2: ='Debt Given By Skalar Cohort Led'!E25 -> 46201 | F2: ='Debt Given By Skalar Cohort Led'!F25 -> 46231 | G2: ='Debt Given By Skalar Cohort Led'!G25 -> 46262 | H2: ='Debt Given By Skalar Cohort Led'!H25 -> 46293 | I2: ='Debt Given By Skalar Cohort Led'!I25 -> 46323 | J2: ='Debt Given By Skalar Cohort Led'!J25 -> 46354
C3: ='Debt Given By Skalar Cohort Led'!C26 -> Outflows (all principal) | D3: ='Debt Given By Skalar Cohort Led'!D26 -> -160000 | E3: ='Debt Given By Skalar Cohort Led'!E26 -> -212000 | F3: ='Debt Given By Skalar Cohort Led'!F26 -> 6000 | G3: ='Debt Given By Skalar Cohort Led'!G26 -> 0 | H3: ='Debt Given By Skalar Cohort Led'!H26 -> 0 | I3: ='Debt Given By Skalar Cohort Led'!I26 -> 0 | J3: ='Debt Given By Skalar Cohort Led'!J26 -> 0
C4: ='Debt Given By Skalar Cohort Led'!C27 -> Inflows | D4: ='Debt Given By Skalar Cohort Led'!D27 -> 0 | E4: ='Debt Given By Skalar Cohort Led'!E27 -> 0 | F4: ='Debt Given By Skalar Cohort Led'!F27 -> 84000 | G4: ='Debt Given By Skalar Cohort Led'!G27 -> 45000 | H4: ='Debt Given By Skalar Cohort Led'!H27 -> 30000 | I4: ='Debt Given By Skalar Cohort Led'!I27 -> 22500 | J4: ='Debt Given By Skalar Cohort Led'!J27 -> 0
C5: ='Debt Given By Skalar Cohort Led'!C28 -> Principal | D5: ='Debt Given By Skalar Cohort Led'!D28 -> 0 | E5: ='Debt Given By Skalar Cohort Led'!E28 -> -2961.5659 | F5: ='Debt Given By Skalar Cohort Led'!F28 -> 76825.993 | G5: ='Debt Given By Skalar Cohort Led'!G28 -> 39410.674 | H5: ='Debt Given By Skalar Cohort Led'!H28 -> 25322.116 | I5: ='Debt Given By Skalar Cohort Led'!I28 -> 11783.627 | J5: ='Debt Given By Skalar Cohort Led'!J28 -> -3991.0647
C6: ='Debt Given By Skalar Cohort Led'!C29 -> Interest (Revenue) | D6: ='Debt Given By Skalar Cohort Led'!D29 -> 0 | E6: ='Debt Given By Skalar Cohort Led'!E29 -> 2961.5659 | F6: ='Debt Given By Skalar Cohort Led'!F29 -> 7174.0067 | G6: ='Debt Given By Skalar Cohort Led'!G29 -> 5589.3264 | H6: ='Debt Given By Skalar Cohort Led'!H29 -> 4677.884 | I6: ='Debt Given By Skalar Cohort Led'!I29 -> 10716.373 | J6: ='Debt Given By Skalar Cohort Led'!J29 -> 3991.0647
C7: ='Debt Given By Skalar Cohort Led'!C30 -> Net | D7: ='Debt Given By Skalar Cohort Led'!D30 -> -160000 | E7: ='Debt Given By Skalar Cohort Led'!E30 -> -212000 | F7: ='Debt Given By Skalar Cohort Led'!F30 -> 90000 | G7: ='Debt Given By Skalar Cohort Led'!G30 -> 45000 | H7: ='Debt Given By Skalar Cohort Led'!H30 -> 30000 | I7: ='Debt Given By Skalar Cohort Led'!I30 -> 22500 | J7: ='Debt Given By Skalar Cohort Led'!J30 -> 0
C8: ='Debt Given By Skalar Cohort Led'!C31 -> Principal Outstanding | D8: ='Debt Given By Skalar Cohort Led'!D31 -> -160000 | E8: ='Debt Given By Skalar Cohort Led'!E31 -> -374961.57 | F8: ='Debt Given By Skalar Cohort Led'!F31 -> -292135.57 | G8: ='Debt Given By Skalar Cohort Led'!G31 -> -252724.9 | H8: ='Debt Given By Skalar Cohort Led'!H31 -> -227402.78 | I8: ='Debt Given By Skalar Cohort Led'!I31 -> -215619.16 | J8: ='Debt Given By Skalar Cohort Led'!J31 -> -219610.22
B11: Debt Taken by Skalar | C11: ='Debt Taken by Skalar Cohort Led'!C25 -> Date | D11: ='Debt Taken by Skalar Cohort Led'!D25 -> 46178 | E11: ='Debt Taken by Skalar Cohort Led'!E25 -> 46201 | F11: ='Debt Taken by Skalar Cohort Led'!F25 -> 46231 | G11: ='Debt Taken by Skalar Cohort Led'!G25 -> 46262 | H11: ='Debt Taken by Skalar Cohort Led'!H25 -> 46293 | I11: ='Debt Taken by Skalar Cohort Led'!I25 -> 46323 | J11: ='Debt Taken by Skalar Cohort Led'!J25 -> 46354
C12: ='Debt Taken by Skalar Cohort Led'!C26 -> Inflows | D12: ='Debt Taken by Skalar Cohort Led'!D26 -> 152000 | E12: ='Debt Taken by Skalar Cohort Led'!E26 -> 178600 | F12: ='Debt Taken by Skalar Cohort Led'!F26 -> 5700 | G12: ='Debt Taken by Skalar Cohort Led'!G26 -> 0 | H12: ='Debt Taken by Skalar Cohort Led'!H26 -> 0 | I12: ='Debt Taken by Skalar Cohort Led'!I26 -> 0 | J12: ='Debt Taken by Skalar Cohort Led'!J26 -> 0
C13: ='Debt Taken by Skalar Cohort Led'!C27 -> Outflows | D13: ='Debt Taken by Skalar Cohort Led'!D27 -> 0 | E13: ='Debt Taken by Skalar Cohort Led'!E27 -> 0 | F13: ='Debt Taken by Skalar Cohort Led'!F27 -> -79800 | G13: ='Debt Taken by Skalar Cohort Led'!G27 -> -42750 | H13: ='Debt Taken by Skalar Cohort Led'!H27 -> -28157.97 | I13: ='Debt Taken by Skalar Cohort Led'!I27 -> 0 | J13: ='Debt Taken by Skalar Cohort Led'!J27 -> 0
C14: ='Debt Taken by Skalar Cohort Led'!C28 -> Principal | D14: ='Debt Taken by Skalar Cohort Led'!D28 -> 0 | E14: ='Debt Taken by Skalar Cohort Led'!E28 -> 1428.2474 | F14: ='Debt Taken by Skalar Cohort Led'!F28 -> -75724.813 | G14: ='Debt Taken by Skalar Cohort Led'!G28 -> -39426.403 | H14: ='Debt Taken by Skalar Cohort Led'!H28 -> -25334.51 | I14: ='Debt Taken by Skalar Cohort Led'!I28 -> 2420.8787 | J14: ='Debt Taken by Skalar Cohort Led'!J28 -> 2532.794
C15: ='Debt Taken by Skalar Cohort Led'!C29 -> Interest (COGS) | D15: ='Debt Taken by Skalar Cohort Led'!D29 -> 0 | E15: ='Debt Taken by Skalar Cohort Led'!E29 -> -1428.2474 | F15: ='Debt Taken by Skalar Cohort Led'!F29 -> -4075.1868 | G15: ='Debt Taken by Skalar Cohort Led'!G29 -> -3323.5972 | H15: ='Debt Taken by Skalar Cohort Led'!H29 -> -2823.4607 | I15: ='Debt Taken by Skalar Cohort Led'!I29 -> -2420.8787 | J15: ='Debt Taken by Skalar Cohort Led'!J29 -> -2532.794
C16: ='Debt Taken by Skalar Cohort Led'!C30 -> Net | D16: ='Debt Taken by Skalar Cohort Led'!D30 -> 152000 | E16: ='Debt Taken by Skalar Cohort Led'!E30 -> 178600 | F16: ='Debt Taken by Skalar Cohort Led'!F30 -> -74100 | G16: ='Debt Taken by Skalar Cohort Led'!G30 -> -42750 | H16: ='Debt Taken by Skalar Cohort Led'!H30 -> -28157.97 | I16: ='Debt Taken by Skalar Cohort Led'!I30 -> 0 | J16: ='Debt Taken by Skalar Cohort Led'!J30 -> 0
C17: ='Debt Taken by Skalar Cohort Led'!C31 -> Principal Outstanding | D17: ='Debt Taken by Skalar Cohort Led'!D31 -> 152000 | E17: ='Debt Taken by Skalar Cohort Led'!E31 -> 332028.25 | F17: ='Debt Taken by Skalar Cohort Led'!F31 -> 262003.43 | G17: ='Debt Taken by Skalar Cohort Led'!G31 -> 222577.03 | H17: ='Debt Taken by Skalar Cohort Led'!H31 -> 197242.52 | I17: ='Debt Taken by Skalar Cohort Led'!I31 -> 199663.4 | J17: ='Debt Taken by Skalar Cohort Led'!J31 -> 202196.19
C19: Revenue | D19: =D6 -> 0 | E19: =E6 -> 2961.5659 | F19: =F6 -> 7174.0067 | G19: =G6 -> 5589.3264 | H19: =H6 -> 4677.884 | I19: =I6 -> 10716.373 | J19: =J6 -> 3991.0647
C20: Cost of Capital (COGS) | D20: =D15 -> 0 | E20: =E15 -> -1428.2474 | F20: =F15 -> -4075.1868 | G20: =G15 -> -3323.5972 | H20: =H15 -> -2823.4607 | I20: =I15 -> -2420.8787 | J20: =J15 -> -2532.794
C21: Outstanding Principal Lended | D21: =D8 -> -160000 | E21: =E8 -> -374961.57 | F21: =F8 -> -292135.57 | G21: =G8 -> -252724.9 | H21: =H8 -> -227402.78 | I21: =I8 -> -215619.16 | J21: =J8 -> -219610.22
C22: Outstanding Principal Borrowed | D22: =D17 -> 152000 | E22: =E17 -> 332028.25 | F22: =F17 -> 262003.43 | G22: =G17 -> 222577.03 | H22: =H17 -> 197242.52 | I22: =I17 -> 199663.4 | J22: =J17 -> 202196.19
C23: Skalar Period Cash Impact | D23: =SUM(D19:D22) -> -8000 | E23: =SUM(E19:E22)-SUM(D21:D22) -> -33400 | F23: =SUM(F19:F22)-SUM(E21:E22) -> 15900 | G23: =SUM(G19:G22)-SUM(F21:F22) -> 2250 | H23: =SUM(H19:H22)-SUM(G21:G22) -> 1842.0295 | I23: =SUM(I19:I22)-SUM(H21:H22) -> 22500 | J23: =SUM(J19:J22)-SUM(I21:I22) -> 0
C24: Check | D24: =D7+D16-D23 -> 0 | E24: =E7+E16-E23 -> 0 | F24: =F7+F16-F23 -> 2.910383e-11 | G24: =G7+G16-G23 -> 0 | H24: =H7+H16-H23 -> -7.2759576e-12 | I24: =I7+I16-I23 -> 0 | J24: =J7+J16-J23 -> 0

Sheet Debt Given By Skalar Cohort Led
B2: IRR for EIR Method | C2: 0.25
C4: Days in Month | D4: =DAY(EOMONTH(D5,0)) -> 30 | E4: =DAY(EOMONTH(E5,0)) -> 30 | F4: =DAY(EOMONTH(F5,0)) -> 31 | G4: =DAY(EOMONTH(G5,0)) -> 31 | H4: =DAY(EOMONTH(H5,0)) -> 30 | I4: =DAY(EOMONTH(I5,0)) -> 31 | J4: =DAY(EOMONTH(J5,0)) -> 30
B5: June 2026 Loan | C5: Date | D5: 46181 | E5: 46201 | F5: 46231 | G5: 46262 | H5: 46293 | I5: 46323 | J5: 46354
C6: Outflows (all principal) | D6: -160000 | E6: -12000 | F6: 6000
C7: Inflows | D7: 0 | F7: 84000 | G7: 45000 | H7: 30000 | I7: 22500
C8: Principal | E8: =MIN(E7-(-D11*POWER((1+$C$2),E$4/365)+D11),-D11) -> -2961.5659 | F8: =MIN(F7-(-E11*POWER((1+$C$2),F$4/365)+E11),-E11) -> 80652.522 | G8: =MIN(G7-(-F11*POWER((1+$C$2),G$4/365)+F11),-F11) -> 43310.414 | H8: =MIN(H7-(-G11*POWER((1+$C$2),H$4/365)+G11),-G11) -> 29167.085 | I8: =MIN(I7-(-H11*POWER((1+$C$2),I$4/365)+H11),-H11) -> 15831.544 | J8: =MIN(J7-(-I11*POWER((1+$C$2),J$4/365)+I11),-I11) -> 0
C9: Interest (Revenue) | E9: =E7-E8 -> 2961.5659 | F9: =F7-F8 -> 3347.4776 | G9: =G7-G8 -> 1689.5856 | H9: =H7-H8 -> 832.91504 | I9: =I7-I8 -> 6668.4558 | J9: =J7-J8 -> 0
C10: Net | D10: =SUM(D6,D7) -> -160000 | E10: =SUM(E6,E7) -> -12000 | F10: =SUM(F6,F7) -> 90000 | G10: =SUM(G6,G7) -> 45000 | H10: =SUM(H6,H7) -> 30000 | I10: =SUM(I6,I7) -> 22500 | J10: =SUM(J6,J7) -> 0
C11: Principal Outstanding | D11: =D6 -> -160000 | E11: =D11+E8+E6 -> -174961.57 | F11: =E11+F8+F6 -> -88309.044 | G11: =F11+G8+G6 -> -44998.629 | H11: =G11+H8+H6 -> -15831.544 | I11: =H11+I8+I6 -> 0 | J11: =I11+J8+J6 -> 0
C12: Check | D12: =D7-D8-D9 -> 0 | E12: =E7-E8-E9 -> 0 | F12: =F7-F8-F9 -> 0 | G12: =G7-G8-G9 -> 0 | H12: =H7-H8-H9 -> 0 | I12: =I7-I8-I9 -> 0 | J12: =J7-J8-J9 -> 0
C13: IRR | D13: =XIRR(D10:J10,D$5:J$5) -> 0.50993114
B15: July 2026 Loan | C15: Date | D15: =D5 -> 46181 | E15: =E5 -> 46201 | F15: =F5 -> 46231 | G15: =G5 -> 46262 | H15: =H5 -> 46293 | I15: =I5 -> 46323 | J15: =J5 -> 46354
C16: Outflows (all principal) | E16: =-250000*0.8 -> -200000
C17: Inflows
C18: Principal | F18: =MIN(F17-(-E21*POWER((1+$C$2),F$4/365)+E21),-E21) -> -3826.5291 | G18: =MIN(G17-(-F21*POWER((1+$C$2),G$4/365)+F21),-F21) -> -3899.7407 | H18: =MIN(H17-(-G21*POWER((1+$C$2),H$4/365)+G21),-G21) -> -3844.969 | I18: =MIN(I17-(-H21*POWER((1+$C$2),I$4/365)+H21),-H21) -> -4047.9175 | J18: =MIN(J17-(-I21*POWER((1+$C$2),J$4/365)+I21),-I21) -> -3991.0647
C19: Interest (Revenue) | F19: =F17-F18 -> 3826.5291 | G19: =G17-G18 -> 3899.7407 | H19: =H17-H18 -> 3844.969 | I19: =I17-I18 -> 4047.9175 | J19: =J17-J18 -> 3991.0647
C20: Net | E20: =SUM(E16,E17) -> -200000 | F20: =SUM(F16,F17) -> 0 | G20: =SUM(G16,G17) -> 0 | H20: =SUM(H16,H17) -> 0 | I20: =SUM(I16,I17) -> 0 | J20: =SUM(J16,J17) -> 0
C21: Principal Outstanding | E21: =D21+E18+E16 -> -200000 | F21: =E21+F18+F16 -> -203826.53 | G21: =F21+G18+G16 -> -207726.27 | H21: =G21+H18+H16 -> -211571.24 | I21: =H21+I18+I16 -> -215619.16 | J21: =I21+J18+J16 -> -219610.22
C22: Check | D22: =D17-D18-D19 -> 0 | E22: =E17-E18-E19 -> 0 | F22: =F17-F18-F19 -> 0 | G22: =G17-G18-G19 -> 0 | H22: =H17-H18-H19 -> 0 | I22: =I17-I18-I19 -> 0 | J22: =J17-J18-J19 -> 0
C23: IRR | D23: =XIRR(E20:J20,E$5:J$5) -> #NUM!
B25: Consolidated Loans | C25: Date | D25: =D5 -> 46181 | E25: =E5 -> 46201 | F25: =F5 -> 46231 | G25: =G5 -> 46262 | H25: =H5 -> 46293 | I25: =I5 -> 46323 | J25: =J5 -> 46354
C26: Outflows (all principal) | D26: =SUM(D6,D16) -> -160000 | E26: =SUM(E6,E16) -> -212000 | F26: =SUM(F6,F16) -> 6000 | G26: =SUM(G6,G16) -> 0 | H26: =SUM(H6,H16) -> 0 | I26: =SUM(I6,I16) -> 0 | J26: =SUM(J6,J16) -> 0
C27: Inflows | D27: =SUM(D7,D17) -> 0 | E27: =SUM(E7,E17) -> 0 | F27: =SUM(F7,F17) -> 84000 | G27: =SUM(G7,G17) -> 45000 | H27: =SUM(H7,H17) -> 30000 | I27: =SUM(I7,I17) -> 22500 | J27: =SUM(J7,J17) -> 0
C28: Principal | D28: =SUM(D8,D18) -> 0 | E28: =SUM(E8,E18) -> -2961.5659 | F28: =SUM(F8,F18) -> 76825.993 | G28: =SUM(G8,G18) -> 39410.674 | H28: =SUM(H8,H18) -> 25322.116 | I28: =SUM(I8,I18) -> 11783.627 | J28: =SUM(J8,J18) -> -3991.0647
C29: Interest (Revenue) | D29: =SUM(D9,D19) -> 0 | E29: =SUM(E9,E19) -> 2961.5659 | F29: =SUM(F9,F19) -> 7174.0067 | G29: =SUM(G9,G19) -> 5589.3264 | H29: =SUM(H9,H19) -> 4677.884 | I29: =SUM(I9,I19) -> 10716.373 | J29: =SUM(J9,J19) -> 3991.0647
C30: Net | D30: =SUM(D10,D20) -> -160000 | E30: =SUM(E10,E20) -> -212000 | F30: =SUM(F10,F20) -> 90000 | G30: =SUM(G10,G20) -> 45000 | H30: =SUM(H10,H20) -> 30000 | I30: =SUM(I10,I20) -> 22500 | J30: =SUM(J10,J20) -> 0
C31: Principal Outstanding | D31: =SUM(D11,D21) -> -160000 | E31: =SUM(E11,E21) -> -374961.57 | F31: =SUM(F11,F21) -> -292135.57 | G31: =SUM(G11,G21) -> -252724.9 | H31: =SUM(H11,H21) -> -227402.78 | I31: =SUM(I11,I21) -> -215619.16 | J31: =SUM(J11,J21) -> -219610.22
C32: Check | D32: =SUM(D26,D27)-D30 -> 0 | E32: =SUM(E26,E27)-E30 -> 0 | F32: =SUM(F26,F27)-F30 -> 0 | G32: =SUM(G26,G27)-G30 -> 0 | H32: =SUM(H26,H27)-H30 -> 0 | I32: =SUM(I26,I27)-I30 -> 0 | J32: =SUM(J26,J27)-J30 -> 0

Sheet Debt Taken by Skalar Cohort Led
B2: IRR for EIR Method | C2: 0.16
B5: June 2026 Loan | C5: Date | D5: 46178 | E5: 46201 | F5: 46231 | G5: 46262 | H5: 46293 | I5: 46323 | J5: 46354
C6: Inflows | D6: =-'Debt Given By Skalar Cohort Led'!D6*0.95 -> 152000 | E6: ='Debt Given By Skalar Cohort Led'!E6*0.95 -> -11400 | F6: ='Debt Given By Skalar Cohort Led'!F6*0.95 -> 5700 | G6: ='Debt Given By Skalar Cohort Led'!G6*0.95 -> 0 | H6: ='Debt Given By Skalar Cohort Led'!H6*0.95 -> 0 | I6: ='Debt Given By Skalar Cohort Led'!I6*0.95 -> 0 | J6: ='Debt Given By Skalar Cohort Led'!J6*0.95 -> 0
C7: Outflows | E7: =MAX(-'Debt Given By Skalar Cohort Led'!E7*0.95,-D11+E9) -> 0 | F7: =MAX(-'Debt Given By Skalar Cohort Led'!F7*0.95,-E11+F9) -> -79800 | G7: =MAX(-'Debt Given By Skalar Cohort Led'!G7*0.95,-F11+G9) -> -42750 | H7: =MAX(-'Debt Given By Skalar Cohort Led'!H7*0.95,-G11+H9) -> -28157.97 | I7: =MAX(-'Debt Given By Skalar Cohort Led'!I7*0.95,-H11+I9) -> 0 | J7: =MAX(-'Debt Given By Skalar Cohort Led'!J7*0.95,-I11+J9) -> 0
C8: Principal | E8: =E7+(D11*POWER((1+$C$2),(E5-D5)/365)-D11) -> 1428.2474 | F8: =F7+(E11*POWER((1+$C$2),(F5-E5)/365)-E11) -> -78056.8 | G8: =G7+(F11*POWER((1+$C$2),(G5-F5)/365)-F11) -> -41866.195 | H8: =H7+(G11*POWER((1+$C$2),(H5-G5)/365)-G11) -> -27805.252 | I8: =I7+(H11*POWER((1+$C$2),(I5-H5)/365)-H11) -> 0 | J8: =J7+(I11*POWER((1+$C$2),(J5-I5)/365)-I11) -> 0
C9: Interest (COGS) | E9: =E7-E8 -> -1428.2474 | F9: =F7-F8 -> -1743.2 | G9: =G7-G8 -> -883.80456 | H9: =H7-H8 -> -352.7185 | I9: =I7-I8 -> 0 | J9: =J7-J8 -> 0
C10: Net | D10: =SUM(D6:D7) -> 152000 | E10: =SUM(E6:E7) -> -11400 | F10: =SUM(F6:F7) -> -74100 | G10: =SUM(G6:G7) -> -42750 | H10: =SUM(H6:H7) -> -28157.97 | I10: =SUM(I6:I7) -> 0 | J10: =SUM(J6:J7) -> 0
C11: Principal Outstanding | D11: =D6 -> 152000 | E11: =D11+E8+E6 -> 142028.25 | F11: =E11+F8+F6 -> 69671.447 | G11: =F11+G8+G6 -> 27805.252 | H11: =G11+H8+H6 -> 0 | I11: =H11+I8+I6 -> 0 | J11: =I11+J8+J6 -> 0
C12: Check | D12: =D7-D8-D9 -> 0 | E12: =E7-E8-E9 -> 0 | F12: =F7-F8-F9 -> 0 | G12: =G7-G8-G9 -> 0 | H12: =H7-H8-H9 -> 0 | I12: =I7-I8-I9 -> 0 | J12: =J7-J8-J9 -> 0
C13: IRR | D13: =XIRR(D10:J10,D$5:J$5) -> 0.16
B15: July 2026 Loan | C15: Date | D15: 46178 | E15: 46201 | F15: 46231 | G15: 46262 | H15: 46293 | I15: 46323 | J15: 46354
C16: Inflows | E16: =-'Debt Given By Skalar Cohort Led'!E16*0.95 -> 190000 | F16: ='Debt Given By Skalar Cohort Led'!F16*0.95 -> 0 | G16: ='Debt Given By Skalar Cohort Led'!G16*0.95 -> 0 | H16: ='Debt Given By Skalar Cohort Led'!H16*0.95 -> 0 | I16: ='Debt Given By Skalar Cohort Led'!I16*0.95 -> 0 | J16: ='Debt Given By Skalar Cohort Led'!J16*0.95 -> 0
C17: Outflows | E17: =MAX(-'Debt Given By Skalar Cohort Led'!E17*0.95,-D21+E19) -> 0 | F17: =MAX(-'Debt Given By Skalar Cohort Led'!F17*0.95,-E21+F19) -> 0 | G17: =MAX(-'Debt Given By Skalar Cohort Led'!G17*0.95,-F21+G19) -> 0 | H17: =MAX(-'Debt Given By Skalar Cohort Led'!H17*0.95,-G21+H19) -> 0 | I17: =MAX(-'Debt Given By Skalar Cohort Led'!I17*0.95,-H21+I19) -> 0 | J17: =MAX(-'Debt Given By Skalar Cohort Led'!J17*0.95,-I21+J19) -> 0
C18: Principal | E18: =E17+(D21*POWER((1+$C$2),(E5-D5)/365)-D21) -> 0 | F18: =F17+(E21*POWER((1+$C$2),(F5-E5)/365)-E21) -> 2331.9868 | G18: =G17+(F21*POWER((1+$C$2),(G5-F5)/365)-F21) -> 2439.7927 | H18: =H17+(G21*POWER((1+$C$2),(H5-G5)/365)-G21) -> 2470.7422 | I18: =I17+(H21*POWER((1+$C$2),(I5-H5)/365)-H21) -> 2420.8787 | J18: =J17+(I21*POWER((1+$C$2),(J5-I5)/365)-I21) -> 2532.794
C19: Interest (COGS) | E19: =E17-E18 -> 0 | F19: =F17-F18 -> -2331.9868 | G19: =G17-G18 -> -2439.7927 | H19: =H17-H18 -> -2470.7422 | I19: =I17-I18 -> -2420.8787 | J19: =J17-J18 -> -2532.794
C20: Net | D20: =SUM(D16:D17) -> 0 | E20: =SUM(E16:E17) -> 190000 | F20: =SUM(F16:F17) -> 0 | G20: =SUM(G16:G17) -> 0 | H20: =SUM(H16:H17) -> 0 | I20: =SUM(I16:I17) -> 0 | J20: =SUM(J16:J17) -> 0
C21: Principal Outstanding | D21: =D16 -> 0 | E21: =D21+E18+E16 -> 190000 | F21: =E21+F18+F16 -> 192331.99 | G21: =F21+G18+G16 -> 194771.78 | H21: =G21+H18+H16 -> 197242.52 | I21: =H21+I18+I16 -> 199663.4 | J21: =I21+J18+J16 -> 202196.19
C22: Check | D22: =D17-D18-D19 -> 0 | E22: =E17-E18-E19 -> 0 | F22: =F17-F18-F19 -> 0 | G22: =G17-G18-G19 -> 0 | H22: =H17-H18-H19 -> 0 | I22: =I17-I18-I19 -> 0 | J22: =J17-J18-J19 -> 0
C23: IRR | D23: =XIRR(E20:J20,E$5:J$5) -> #NUM!
B25: Consolidated Loans | C25: Date | D25: =D5 -> 46178 | E25: =E5 -> 46201 | F25: =F5 -> 46231 | G25: =G5 -> 46262 | H25: =H5 -> 46293 | I25: =I5 -> 46323 | J25: =J5 -> 46354
C26: Inflows | D26: =SUM(D6,D16) -> 152000 | E26: =SUM(E6,E16) -> 178600 | F26: =SUM(F6,F16) -> 5700 | G26: =SUM(G6,G16) -> 0 | H26: =SUM(H6,H16) -> 0 | I26: =SUM(I6,I16) -> 0 | J26: =SUM(J6,J16) -> 0
C27: Outflows | D27: =SUM(D7,D17) -> 0 | E27: =SUM(E7,E17) -> 0 | F27: =SUM(F7,F17) -> -79800 | G27: =SUM(G7,G17) -> -42750 | H27: =SUM(H7,H17) -> -28157.97 | I27: =SUM(I7,I17) -> 0 | J27: =SUM(J7,J17) -> 0
C28: Principal | D28: =SUM(D8,D18) -> 0 | E28: =SUM(E8,E18) -> 1428.2474 | F28: =SUM(F8,F18) -> -75724.813 | G28: =SUM(G8,G18) -> -39426.403 | H28: =SUM(H8,H18) -> -25334.51 | I28: =SUM(I8,I18) -> 2420.8787 | J28: =SUM(J8,J18) -> 2532.794
C29: Interest (COGS) | D29: =SUM(D9,D19) -> 0 | E29: =SUM(E9,E19) -> -1428.2474 | F29: =SUM(F9,F19) -> -4075.1868 | G29: =SUM(G9,G19) -> -3323.5972 | H29: =SUM(H9,H19) -> -2823.4607 | I29: =SUM(I9,I19) -> -2420.8787 | J29: =SUM(J9,J19) -> -2532.794
C30: Net | D30: =SUM(D10,D20) -> 152000 | E30: =SUM(E10,E20) -> 178600 | F30: =SUM(F10,F20) -> -74100 | G30: =SUM(G10,G20) -> -42750 | H30: =SUM(H10,H20) -> -28157.97 | I30: =SUM(I10,I20) -> 0 | J30: =SUM(J10,J20) -> 0
C31: Principal Outstanding | D31: =SUM(D11,D21) -> 152000 | E31: =SUM(E11,E21) -> 332028.25 | F31: =SUM(F11,F21) -> 262003.43 | G31: =SUM(G11,G21) -> 222577.03 | H31: =SUM(H11,H21) -> 197242.52 | I31: =SUM(I11,I21) -> 199663.4 | J31: =SUM(J11,J21) -> 202196.19
C32: Check | D32: =SUM(D26:D27)-D30 -> 0 | E32: =SUM(E26:E27)-E30 -> 0 | F32: =SUM(F26:F27)-F30 -> 0 | G32: =SUM(G26:G27)-G30 -> 0 | H32: =SUM(H26:H27)-H30 -> 0 | I32: =SUM(I26:I27)-I30 -> 0 | J32: =SUM(J26:J27)-J30 -> 0
C33: IRR | D33: =XIRR(D30:J30,D$5:J$5) -> -0.99035013

Sheet Structure
B2: 1Have Transacted Amount Ledger for every underlying company
B3: 2Have tab of inflows, outflows per company con calculo de principal/interest por cohorte y consolidado (igual al debt given tab)
B4: 2.1Un Extra* Track Revenue per company per month internally - basado en consolidado de interes por compania
B5: 3 Companies get consolidated into cross-cohorts - from point 2
B6: 4. Generate debt taken from point 3 - input GC transaction dates
B7: 5 Generate accounting from points 3,4
B8: 6. Generate Payments "ToDo" based on netting for each company / GC
B10: Transacted USD Amount (neg from Skalar, pos to Skalar) | C10: Loan Cohort | D10: Skalar Contraparty | E10: Date | F10: Type
B11: -160000 | C11: 46174 | D11: Kindroid | E11: 46178 | F11: Investment Request
B12: -200000 | C12: 46204 | D12: Kindroid | E12: 46178 | F12: Investment Request
F13: Under/Over
F14: Payment Due
C15: 46199 | E15: December 1 2026 | F15: Under/Over
